MANIFEST.in
README.md
requirements.txt
setup.py
bin/yagi-event
bin/yagi-feed
tests/unit/__init__.py
tests/unit/test_atompub.py
tests/unit/test_auth.py
tests/unit/test_base_handler.py
tests/unit/test_cufpub.py
tests/unit/test_feed.py
tests/unit/test_http_connection.py
tests/unit/test_notification.py
tests/unit/test_notification_options.py
tests/unit/test_serialization.py
tests/unit/test_shoebox_handler.py
tests/unit/test_stacktach_ping.py
tests/unit/utils.py
yagi/__init__.py
yagi/auth.py
yagi/commandline.py
yagi/config.py
yagi/consumer.py
yagi/event_worker.py
yagi/filters.py
yagi/http_util.py
yagi/log.py
yagi/stats.py
yagi/utils.py
yagi.egg-info/PKG-INFO
yagi.egg-info/SOURCES.txt
yagi.egg-info/dependency_links.txt
yagi.egg-info/not-zip-safe
yagi.egg-info/pbr.json
yagi.egg-info/requires.txt
yagi.egg-info/top_level.txt
yagi/broker/__init__.py
yagi/broker/rabbit.py
yagi/feed/__init__.py
yagi/feed/feed.py
yagi/handler/__init__.py
yagi/handler/atompub_handler.py
yagi/handler/cuf_pub_handler.py
yagi/handler/http_connection.py
yagi/handler/notification.py
yagi/handler/notification_options.py
yagi/handler/notification_payload.py
yagi/handler/pubsubhubbub_handler.py
yagi/handler/redis_handler.py
yagi/handler/shoebox_handler.py
yagi/handler/stacktach_ping_handler.py
yagi/persistence/__init__.py
yagi/persistence/devnull.py
yagi/persistence/redis_driver.py
yagi/serializer/__init__.py
yagi/serializer/atom.py
yagi/serializer/cuf.py
yagi/serializer/paged_feed.py