Metadata-Version: 1.1
Name: yagi
Version: 0.20
Summary: A PubSubHubBub Publisher and ATOM feed generator that can consume events from multiple input sources and publish them to standard PSHB hubs
Home-page: https://github.com/rackerlabs/yagi
Author: Matthew Dietz, Monsyne Dragon
Author-email: matthew.dietz@gmail.com, mdragon@rackspace.com
License: Apache License (2.0)
Keywords: PubSubHubBub notifications events ATOM RSS
Platform: UNKNOWN
Classifier: Development Status :: 3 - Alpha
Classifier: License :: OSI Approved :: Apache Software License
Classifier: Operating System :: POSIX :: Linux
Classifier: Programming Language :: Python :: 2.6
